[
  {
    "title": "Become a Calculus 1 Master",
    "instructor": "Krista King",
    "rating": 4.7,
    "description": "Learn everything from Calculus 1, then test your knowledge with 600+ practice questions.",
    "price": 74.99,
    "image": "images/logo.png",
    "url": "https://www.udemy.com/course/calculus1/?couponCode=LETSLEARNNOW",
    "provider": "Udemy",
    "level": "All Levels",
    "duration": "13 hours"
  },
  {
    "title": "Become a Probability & Statistics Master",
    "instructor": "Krista King",
    "rating": 4.7,
    "description": "Learn everything from Probability & Statistics, then test your knowledge with 600+ practice questions.",
    "price": 74.99,
    "image": "images/logo.png",
    "url": "https://www.udemy.com/course/statistics-probability/?couponCode=LETSLEARNNOW",
    "provider": "Udemy",
    "level": "All Levels",
    "duration": "15 hours"
  },
  {
    "title": "Become an Algebra Master",
    "instructor": "Krista King",
    "rating": 4.8,
    "description": "Learn everything from Algebra 1 and Algebra 2, then test your knowledge with 1,150+ practice questions.",
    "price": 74.99,
    "image": "images/logo.png",
    "url": "https://www.udemy.com/course/integralcalc-algebra/?couponCode=LETSLEARNNOW",
    "provider": "Udemy",
    "level": "All Levels",
    "duration": "16.5 hours"
  },
  {
    "title": "Become a Calculus 2 Master",
    "instructor": "Krista King",
    "rating": 4.6,
    "description": "Learn everything from Calculus 2, then test your knowledge with 830+ practice questions.",
    "price": 74.99,
    "image": "images/logo.png",
    "url": "https://www.udemy.com/course/calculus-2/?couponCode=LETSLEARNNOW",
    "provider": "Udemy",
    "level": "All Levels",
    "duration": "29 hours"
  },
  {
    "title": "Master the Fundamentals of Math",
    "instructor": "Krista King",
    "rating": 4.8,
    "description": "Learn everything from the basics of math, then test your knowledge with 510+ practice questions.",
    "price": 74.99,
    "image": "images/logo.png",
    "url": "https://www.udemy.com/course/fundamentals-of-math/?couponCode=LETSLEARNNOW",
    "provider": "Udemy",
    "level": "All Levels",
    "duration": "5 hours"
  },
  {
    "title": "11 Days Math Challenge: Master Basics of Mathematics",
    "instructor": "Jackson Kailath",
    "rating": 4.4,
    "description": "Build a solid mathematics foundation by disciplining yourself only for 11 days!",
    "price": 69.99,
    "image": "images/logo.png",
    "url": "https://www.udemy.com/course/math-fundamentals/?couponCode=LETSLEARNNOW",
    "provider": "Udemy",
    "level": "Beginner",
    "duration": "19.5 hours"
  },
  {
    "title": "Become a Trigonometry & Precalculus Master",
    "instructor": "Krista King",
    "rating": 4.8,
    "description": "Learn everything from Trigonometry and Precalculus, then test your knowledge with 470+ practice questions.",
    "price": 74.99,
    "image": "images/logo.png",
    "url": "https://www.udemy.com/course/trig-by-krista-king/?couponCode=LETSLEARNNOW",
    "provider": "Udemy",
    "level": "All Levels",
    "duration": "19.5 hours"
  },
  {
    "title": "Become a Calculus 3 Master",
    "instructor": "Krista King",
    "rating": 4.7,
    "description": "Learn everything from Calculus 3, then test your knowledge with 780+ practice questions.",
    "price": 74.99,
    "image": "images/logo.png",
    "url": "https://www.udemy.com/course/calculus-3/?couponCode=LETSLEARNNOW",
    "provider": "Udemy",
    "level": "All Levels",
    "duration": "24.5 hours"
  },
  {
    "title": "Become a Linear Algebra Master",
    "instructor": "Krista King",
    "rating": 4.7,
    "description": "Learn everything from Linear Algebra, then test your knowledge with 400+ practice questions.",
    "price": 74.99,
    "image": "images/logo.png",
    "url": "https://www.udemy.com/course/linear-algebra-course/?couponCode=LETSLEARNNOW",
    "provider": "Udemy",
    "level": "All Levels",
    "duration": "16 hours"
  },
  {
    "title": "Master Linear Algebra: Theory and Implementation in Code",
    "instructor": "Mike X Cohen",
    "rating": 4.7,
    "description": "Learn concepts in linear algebra and matrix analysis, and implement them in MATLAB and Python.",
    "price": 74.99,
    "image": "images/logo.png",
    "url": "https://www.udemy.com/course/linear-algebra-theory-and-implementation/?couponCode=LETSLEARNNOW",
    "provider": "Udemy",
    "level": "All Levels",
    "duration": "34 hours"
  },
  {
    "title": "Calculus 2, part 2 of 2: Sequences and Series",
    "instructor": "Hania Uscka-Wehlou and 1 other",
    "rating": 4.9,
    "description": "Single variable Calculus: sequences and series of numbers and functions.",
    "price": 34.99,
    "image": "images/logo.png",
    "url": "https://www.udemy.com/course/calculus-2-p2/?couponCode=LETSLEARNNOW",
    "provider": "Udemy",
    "level": "All Levels",
    "duration": "60.5 hours"
  },
  {
    "title": "Workshop in Probability and Statistics",
    "instructor": "George Ingersoll",
    "rating": 4.7,
    "description": "Fundamentals of statistics for work or school.",
    "price": 74.99,
    "image": "images/logo.png",
    "url": "https://www.udemy.com/course/statshelp/",
    "provider": "Udemy",
    "level": "All Levels",
    "duration": "21.5 hours"
  },
  {
    "title": "Complete High Speed Vedic Math Course",
    "instructor": "Gaurav Tekriwal",
    "rating": 4.6,
    "description": "Learn the world's fastest mental math system.",
    "price": 74.99,
    "image": "images/logo.png",
    "url": "https://www.udemy.com/course/vedicmaths/",
    "provider": "Udemy",
    "level": "All Levels",
    "duration": "14.5 hours"
  },
  {
    "title": "Discrete Mathematics",
    "instructor": "Miran Fattah",
    "rating": 4.6,
    "description": "Master Discrete Math with 400+ practice questions and quizzes.",
    "price": 74.99,
    "image": "images/logo.png",
    "url": "https://www.udemy.com/course/discrete-math/",
    "provider": "Udemy",
    "level": "All Levels",
    "duration": "19 hours"
  },
  {
    "title": "Become a Geometry Master",
    "instructor": "Krista King",
    "rating": 4.8,
    "description": "Learn everything from Geometry, then test your knowledge with 730+ practice questions.",
    "price": 74.99,
    "image": "images/logo.png",
    "url": "https://www.udemy.com/course/geometry-basics/",
    "provider": "Udemy",
    "level": "All Levels",
    "duration": "9.5 hours"
  },
  {
    "title": "Master Math by Coding in Python",
    "instructor": "Codestars, Mike X Cohen",
    "rating": 4.7,
    "description": "Embark on a Python journey to learn a multitude of math essentials.",
    "price": 74.99,
    "image": "images/logo.png",
    "url": "https://www.udemy.com/course/math-with-python/",
    "provider": "Udemy",
    "level": "All Levels",
    "duration": "37.5 hours"
  },
  {
    "title": "Coding for Kids: Learn Scratch, Python, Robotics, HTML & CSS",
    "instructor": "Robolabz STEM School",
    "rating": 4.5,
    "description": "Be a technology creator! Program games, 3D design, animations, websites & more.",
    "price": 74.99,
    "image": "images/logo.png",
    "url": "https://www.udemy.com/course/robotics-programming-stem-course-for-kids/",
    "provider": "Udemy",
    "level": "Beginner",
    "duration": "16 hours"
  },
  {
    "title": "Core Spatial Data Analysis: Introductory GIS with R and QGIS",
    "instructor": "Minerva Singh",
    "rating": 4.3,
    "description": "Become proficient in spatial data analysis using R & QGIS.",
    "price": 69.99,
    "image": "images/logo.png",
    "url": "https://www.udemy.com/course/core-spatial-data-analysis-with-r-and-qgis/?couponCode=LETSLEARNNOW",
    "provider": "Udemy",
    "level": "All Levels",
    "duration": "2.5 hours"
  },
  {
    "title": "ArcGIS Desktop For Spatial Analysis: Go From Basic To Pro",
    "instructor": "Minerva Singh",
    "rating": 4.4,
    "description": "Spatial Data Analysis With ArcGIS Desktop: Master GIS Techniques and Open Doors to Amazing Geospatial Careers",
    "price": 69.99,
    "image": "images/logo.png",
    "url": "https://www.udemy.com/course/arcgis-desktop-for-spatial-analysis-go-from-basic-to-pro/",
    "provider": "Udemy",
    "level": "Beginner",
    "duration": "5 hours"
  },
  {
    "title": "Learn Algebra The Easy Way!",
    "instructor": "Organic Chemistry Tutor",
    "rating": 4.5,
    "description": "Algebra Review - Slope, Graphing Linear Equations, Exponents, Factoring, Solving Quadratic Equations, & Radicals",
    "price": 64.99,
    "image": "images/logo.png",
    "url": "https://www.udemy.com/course/algebracourse7245/",
    "provider": "Udemy",
    "level": "Beginner",
    "duration": "21 hours"
  },
  {
    "title": "Master Discrete Mathematics: Sets, Math Logic, and More",
    "instructor": "Grant Hall",
    "rating": 4.8,
    "description": "Master Discrete Mathematics: Learn and master all of Discrete Math - Logic, Set Theory, Combinatorics, Graph Theory, Etc",
    "price": 54.99,
    "image": "images/logo.png",
    "url": "https://www.udemy.com/course/master-discrete-mathematics/",
    "provider": "Udemy",
    "level": "All Levels",
    "duration": "7 hours"
  },
  {
    "title": "Calculus 1 with the Math Sorcerer",
    "instructor": "The Math Sorcerer",
    "rating": 4.6,
    "description": "The ULTIMATE Calculus 1 Course! Hundreds of Videos and Tons of Assignments with Solutions:)",
    "price": 69.99,
    "image": "images/logo.png",
    "url": "https://www.udemy.com/course/calculus-1-with-the-math-sorcerer/",
    "provider": "Udemy",
    "level": "All Levels",
    "duration": "16.5 hours"
  },
  {
    "title": "College Algebra with the Math Sorcerer",
    "instructor": "The Math Sorcerer",
    "rating": 4.7,
    "description": "College Algebra Course with HUNDREDS of Video Examples:)",
    "price": 64.99,
    "image": "images/logo.png",
    "url": "https://www.udemy.com/course/college-algebra-with-the-math-sorcerer/",
    "provider": "Udemy",
    "level": "Beginner",
    "duration": "10 hours"
  },
  {
    "title": "Introduction to Probability and Statistics",
    "instructor": "Dane McGuckian",
    "rating": 4.4,
    "description": "A college level first course in Statistics",
    "price": 74.99,
    "image": "images/logo.png",
    "url": "https://www.udemy.com/course/introduction-to-probability-and-statistics/",
    "provider": "Udemy",
    "level": "All Levels",
    "duration": "8.5 hours"
  },
  {
    "title": "Linear Algebra and Geometry 1",
    "instructor": "Hania Uscka-Wehlou, Martin Wehlou",
    "rating": 4.9,
    "description": "Systems of equations, matrices, determinants, vectors, and geometry of straight lines and planes in the 3-space",
    "price": 74.99,
    "image": "images/logo.png",
    "url": "https://www.udemy.com/course/linear-algebra-and-geometry-1/",
    "provider": "Udemy",
    "level": "All Levels",
    "duration": "26 hours"
  },
  {
    "title": "Mathematical Logic",
    "instructor": "edX",
    "rating": 4.2,
    "description": "Learn propositional and predicate logic for mathematics.",
    "price": "Free",
    "image": "images/logo.png",
    "url": "https://www.edx.org/course/mathematical-logic",
    "provider": "edX",
    "level": "Intermediate",
    "duration": "12"
  }
]
